deepbrain/__init__.py
deepbrain/extractor.py
deepbrain/models/.DS_Store
deepbrain/models/graph.pb
deepbrain-0.1.data/scripts/deepbrain-extractor
deepbrain-0.1.dist-info/METADATA
deepbrain-0.1.dist-info/RECORD
deepbrain-0.1.dist-info/WHEEL
deepbrain-0.1.dist-info/top_level.txt
