Metadata-Version: 2.1
Name: deepbrain
Version: 0.1
Summary: Deep Learning-based tools for processing brain images
Home-page: http://github.com/iitzco/deepbrain
Author: Ivan Itzcovich
Author-email: i.itzcovich@gmail.com
License: MIT
Keywords: deep-learning machine-learning tensorflow ai
Platform: any
Classifier: Programming Language :: Python :: 3.5
Classifier: Programming Language :: Python :: 3.6
Classifier: Programming Language :: Python :: 3.7
Requires-Python: >3.5
Requires-Dist: nibabel
Requires-Dist: scikit-image
Requires-Dist: tensorflow
